<?xml version="1.0" encoding="UTF-8" ?>
<XMLDB PATH="mod/ctfflag/db" VERSION="20260608" COMMENT="CTF flag activity"
    xmlns:xsi="http://www.w3.org/2001/XMLSchema-instance"
    xsi:noNamespaceSchemaLocation="../../../lib/xmldb/xmldb.xsd">
  <TABLES>
    <TABLE NAME="ctfflag" COMMENT="CTF flag activity instances">
      <FIELDS>
        <FIELD NAME="id" TYPE="int" LENGTH="10" NOTNULL="true" SEQUENCE="true"/>
        <FIELD NAME="course" TYPE="int" LENGTH="10" NOTNULL="true" SEQUENCE="false"/>
        <FIELD NAME="name" TYPE="char" LENGTH="255" NOTNULL="true" SEQUENCE="false"/>
        <FIELD NAME="intro" TYPE="text" NOTNULL="false" SEQUENCE="false"/>
        <FIELD NAME="introformat" TYPE="int" LENGTH="4" NOTNULL="true" DEFAULT="0" SEQUENCE="false"/>
        <FIELD NAME="expected_flag_regex" TYPE="char" LENGTH="255" NOTNULL="true" SEQUENCE="false"/>
        <FIELD NAME="xp_award" TYPE="int" LENGTH="10" NOTNULL="true" DEFAULT="0" SEQUENCE="false"/>
        <FIELD NAME="completion_required" TYPE="int" LENGTH="1" NOTNULL="true" DEFAULT="1" SEQUENCE="false"/>
        <FIELD NAME="timecreated" TYPE="int" LENGTH="10" NOTNULL="true" DEFAULT="0" SEQUENCE="false"/>
        <FIELD NAME="timemodified" TYPE="int" LENGTH="10" NOTNULL="true" DEFAULT="0" SEQUENCE="false"/>
      </FIELDS>
      <KEYS>
        <KEY NAME="primary" TYPE="primary" FIELDS="id"/>
        <KEY NAME="course" TYPE="foreign" FIELDS="course" REFTABLE="course" REFFIELDS="id"/>
      </KEYS>
    </TABLE>
    <TABLE NAME="ctfflag_submissions" COMMENT="Learner flag submissions">
      <FIELDS>
        <FIELD NAME="id" TYPE="int" LENGTH="10" NOTNULL="true" SEQUENCE="true"/>
        <FIELD NAME="ctfflagid" TYPE="int" LENGTH="10" NOTNULL="true" SEQUENCE="false"/>
        <FIELD NAME="userid" TYPE="int" LENGTH="10" NOTNULL="true" SEQUENCE="false"/>
        <FIELD NAME="success" TYPE="int" LENGTH="1" NOTNULL="true" DEFAULT="0" SEQUENCE="false"/>
        <FIELD NAME="timecreated" TYPE="int" LENGTH="10" NOTNULL="true" DEFAULT="0" SEQUENCE="false"/>
      </FIELDS>
      <KEYS>
        <KEY NAME="primary" TYPE="primary" FIELDS="id"/>
        <KEY NAME="ctfflagid" TYPE="foreign" FIELDS="ctfflagid" REFTABLE="ctfflag" REFFIELDS="id"/>
        <KEY NAME="userid" TYPE="foreign" FIELDS="userid" REFTABLE="user" REFFIELDS="id"/>
      </KEYS>
      <INDEXES>
        <INDEX NAME="ctfflag_user" UNIQUE="false" FIELDS="ctfflagid, userid"/>
      </INDEXES>
    </TABLE>
  </TABLES>
</XMLDB>
